pcdviz/__init__.py
pcdviz/main.py
pcdviz/util.py
pcdviz/visualizer.py
pcdviz/config/__init__.py
pcdviz/config/config.py
pcdviz/dataset/__init__.py
pcdviz/dataset/base_dataset.py
pcdviz/dataset/custom_dataset.py
pcdviz/dataset/kitti.py
pcdviz/dataset/nuscenes.py
pcdviz/dataset/waymo.py
pcdviz-0.0.3.data/data/pcdviz/config/dataset_visualize.yaml
pcdviz-0.0.3.data/data/pcdviz/config/frame_visualize.yaml
pcdviz-0.0.3.data/data/pcdviz/config/frame_visualize_callback.yaml
pcdviz-0.0.3.data/data/pcdviz/config/frame_visualize_filters.yaml
pcdviz-0.0.3.data/data/pcdviz/config/multi_pointcloud.yaml
pcdviz-0.0.3.data/data/pcdviz/data/custom/label/000005.txt
pcdviz-0.0.3.data/data/pcdviz/data/custom/prediction/000005.txt
pcdviz-0.0.3.data/data/pcdviz/data/custom/velodyne/000005.bin
pcdviz-0.0.3.data/data/pcdviz/data/kitti/training/calib/000003.txt
pcdviz-0.0.3.data/data/pcdviz/data/kitti/training/calib/000004.txt
pcdviz-0.0.3.data/data/pcdviz/data/kitti/training/calib/000005.txt
pcdviz-0.0.3.data/data/pcdviz/data/kitti/training/label_2/000003.txt
pcdviz-0.0.3.data/data/pcdviz/data/kitti/training/label_2/000004.txt
pcdviz-0.0.3.data/data/pcdviz/data/kitti/training/label_2/000005.txt
pcdviz-0.0.3.data/data/pcdviz/data/kitti/training/velodyne/000003.bin
pcdviz-0.0.3.data/data/pcdviz/data/kitti/training/velodyne/000004.bin
pcdviz-0.0.3.data/data/pcdviz/data/kitti/training/velodyne/000005.bin
pcdviz-0.0.3.dist-info/LICENSE
pcdviz-0.0.3.dist-info/METADATA
pcdviz-0.0.3.dist-info/WHEEL
pcdviz-0.0.3.dist-info/entry_points.txt
pcdviz-0.0.3.dist-info/top_level.txt
pcdviz-0.0.3.dist-info/RECORD
