Metadata-Version: 2.1
Name: pcdviz
Version: 0.0.3
Summary: point cloud viz
Home-page: https://github.com/daohu527/pcdviz
Author: daohu527
Author-email: daohu527@gmail.com
Project-URL: Bug Tracker, https://github.com/daohu527/pcdviz/issues
Classifier: Programming Language :: Python :: 3
Classifier: License :: OSI Approved :: Apache Software License
Classifier: Operating System :: OS Independent
Requires-Python: >=3.6
License-File: LICENSE
Requires-Dist: open3d
Requires-Dist: numpy
Requires-Dist: pyyaml
